openwisp/sphinx/theme/VERSION
openwisp/sphinx/theme/__init__.py
openwisp/sphinx/theme/footer.html
openwisp/sphinx/theme/theme.conf
openwisp/sphinx/theme/static/css/openwisp-sphinx-theme.css
openwisp/sphinx/theme/static/js/theme.js
openwisp_sphinx_theme-1.0.2.dist-info/LICENSE
openwisp_sphinx_theme-1.0.2.dist-info/METADATA
openwisp_sphinx_theme-1.0.2.dist-info/WHEEL
openwisp_sphinx_theme-1.0.2.dist-info/entry_points.txt
openwisp_sphinx_theme-1.0.2.dist-info/top_level.txt
openwisp_sphinx_theme-1.0.2.dist-info/RECORD
